atom2preservica/__init__.py
atom2preservica/__main__.py
atom2preservica/oai_db.py
atom2preservica-0.1.1.dist-info/LICENSE
atom2preservica-0.1.1.dist-info/METADATA
atom2preservica-0.1.1.dist-info/WHEEL
atom2preservica-0.1.1.dist-info/top_level.txt
atom2preservica-0.1.1.dist-info/RECORD
