Metadata-Version: 2.2
Name: atom2preservica
Version: 0.1.1
Summary: Python library for the Preservica API
Home-page: https://github.com/carj/atom2preservica
Author: James Carr
Author-email: drjamescarr@gmail.com
License: Apache License 2.0
Project-URL: Documentation, https://github.com/carj/atom2preservica
Project-URL: Source, https://github.com/carj/atom2preservica
Project-URL: Discussion Forum, https://github.com/carj/atom2preservica
Keywords: Preservica API Preservation,AccessToMemory,AtoM
Classifier: Programming Language :: Python :: 3
Classifier: Programming Language :: Python :: 3.8
Classifier: Programming Language :: Python :: 3.9
Classifier: Programming Language :: Python :: 3.10
Classifier: Programming Language :: Python :: 3.11
Classifier: Programming Language :: Python :: 3.12
Classifier: License :: OSI Approved :: Apache Software License
Classifier: Operating System :: OS Independent
Classifier: Topic :: System :: Archiving
License-File: LICENSE
Requires-Dist: pyPreservica
Requires-Dist: pyAtoM
Requires-Dist: tinydb
Requires-Dist: Sickle
Dynamic: author
Dynamic: author-email
Dynamic: classifier
Dynamic: description
Dynamic: description-content-type
Dynamic: home-page
Dynamic: keywords
Dynamic: license
Dynamic: project-url
Dynamic: requires-dist
Dynamic: summary
